flycheck_gitchart.py
gitchart.py
gitchart/__init__.py
gitchart/gitchart.py
gitchart-2.0.2.dist-info/LICENSE.txt
gitchart-2.0.2.dist-info/METADATA
gitchart-2.0.2.dist-info/WHEEL
gitchart-2.0.2.dist-info/entry_points.txt
gitchart-2.0.2.dist-info/top_level.txt
gitchart-2.0.2.dist-info/RECORD
