Metadata-Version: 2.1
Name: gitchart
Version: 2.0.2
Summary: Generate statistic charts on Git repositories.
Home-page: https://github.com/flashcode/gitchart
Author: Sébastien Helleu
Author-email: flashcode@flashtux.org
License: GPL3
Keywords: git chart pygal
Platform: UNKNOWN
Classifier: Development Status :: 5 - Production/Stable
Classifier: Environment :: Console
Classifier: Intended Audience :: Developers
Classifier: License :: OSI Approved :: GNU General Public License v3 or later (GPLv3+)
Classifier: Natural Language :: English
Classifier: Operating System :: OS Independent
Classifier: Programming Language :: Python
Classifier: Programming Language :: Python :: 3
Classifier: Topic :: Software Development :: Version Control
Requires-Dist: pygal
